[{"Serial": "0", "ID": "AAH03JABiAAJKjTAjl", "ExposedMoment": "2012-06-22 17:22:03", "ExposedNo": "1"}, {"Serial": "1", "ID": "AAH03JABiAAJKjWAQb", "ExposedMoment": "2012-06-22 17:23:02", "ExposedNo": "1"}, {"Serial": "2", "ID": "AAH03JABeAANU1vAAZ", "ExposedMoment": "2012-06-22 17:24:46", "ExposedNo": "2"}, {"Serial": "3", "ID": "AAH03JABeAANU2HAiB", "ExposedMoment": "2012-06-22 17:25:29", "ExposedNo": "1"}, {"Serial": "4", "ID": "AAH03JABeAANU2XAhk", "ExposedMoment": "2012-06-22 17:30:39", "ExposedNo": "1"}, {"Serial": "5", "ID": "AAH03JABeAANU1BAAY", "ExposedMoment": "2012-06-22 18:21:25", "ExposedNo": "1"}, {"Serial": "6", "ID": "AAH03JABiAAJKjcALD", "ExposedMoment": "2012-06-22 20:51:49", "ExposedNo": "1"}, {"Serial": "7", "ID": "AAH03JABeAANU10AB5", "ExposedMoment": "2012-06-22 20:52:37", "ExposedNo": "1"}, {"Serial": "8", "ID": "AAH03JABeAANU1qADd", "ExposedMoment": "2012-06-22 20:52:48", "ExposedNo": "1"}, {"Serial": "9", "ID": "AAH03JABiAAJKjVANZ", "ExposedMoment": "2012-06-23 09:26:13", "ExposedNo": "1"}, {"Serial": "10", "ID": "AAH03JABhAAAFVXABZ", "ExposedMoment": "2012-06-23 09:26:22", "ExposedNo": "1"}, {"Serial": "11", "ID": "AAH03JABeAANU2PAK0", "ExposedMoment": "2012-06-23 09:26:43", "ExposedNo": "1"}, {"Serial": "12", "ID": "AAH03JABeAANU1CAlJ", "ExposedMoment": "2012-06-23 11:10:50", "ExposedNo": "2"}, {"Serial": "13", "ID": "AAH03JABeAANU1xAeh", "ExposedMoment": "2012-06-23 11:10:56", "ExposedNo": "1"}, {"Serial": "14", "ID": "AAH03JABeAANU2QAcH", "ExposedMoment": "2012-06-23 11:11:08", "ExposedNo": "1"}, {"Serial": "15", "ID": "AAH03JABeAANU0qABo", "ExposedMoment": "2012-06-23 11:11:27", "ExposedNo": "3"}, {"Serial": "16", "ID": "AAH03JABiAAJKjUAnm", "ExposedMoment": "2012-06-23 11:12:04", "ExposedNo": "1"}, {"Serial": "17", "ID": "AAH03JABeAANU1MALS", "ExposedMoment": "2012-06-24 06:08:31", "ExposedNo": "1"}, {"Serial": "18", "ID": "AAH03JABiAAJKjhApx", "ExposedMoment": "2012-06-24 09:04:28", "ExposedNo": "1"}]